model3d/__init__.py
model3d/geometry/__init__.py
model3d/geometry/mesh.py
model3d/geometry/plane.py
model3d/geometry/vector3d.py
model3d-0.1.0.dist-info/LICENSE
model3d-0.1.0.dist-info/METADATA
model3d-0.1.0.dist-info/WHEEL
model3d-0.1.0.dist-info/top_level.txt
model3d-0.1.0.dist-info/RECORD
