Metadata-Version: 2.2
Name: model3d
Version: 0.1.0
Summary: A 3D geometry library that provides a vector3d class for performing 3D vector operations using NumPy.
Author-email: Nicolo Bencini <nicbencini@gmail.com>
Project-URL: Homepage, https://github.com/nicbencini/model3d
Project-URL: Issues, https://github.com/nicbencini/model3d/issues
Classifier: Programming Language :: Python :: 3
Classifier: License :: OSI Approved :: MIT License
Classifier: Operating System :: OS Independent
Requires-Python: >=3.8
License-File: LICENSE
Requires-Dist: numpy
